{"py/object": "rasa.core.featurizers.tracker_featurizers.MaxHistoryTrackerFeaturizer", "state_featurizer": {"py/object": "rasa.core.featurizers.single_state_featurizer.SingleStateFeaturizer", "_default_feature_states": {"intent": {"ask_func_list": 0, "ask_name": 1, "back": 2, "buy_watch": 3, "bye": 4, "give_name": 5, "greet": 6, "nlu_fallback": 7, "out_of_scope": 8, "purchase_process": 9, "restart": 10, "return_policy": 11, "select_brand": 12, "session_start": 13, "specify_gender": 14, "thank": 15, "track_order": 16}, "action_name": {"action_listen": 0, "action_restart": 1, "action_session_start": 2, "action_default_fallback": 3, "action_deactivate_loop": 4, "action_revert_fallback_events": 5, "action_default_ask_affirmation": 6, "action_default_ask_rephrase": 7, "action_two_stage_fallback": 8, "action_unlikely_intent": 9, "action_back": 10, "...": 11, "action_extract_slots": 12, "utter_greet": 13, "utter_greet_with_name": 14, "utter_bye": 15, "utter_unclear": 16, "utter_func_list": 17, "utter_thank": 18, "utter_ask_name": 19, "utter_specify_gender": 20, "action_recommend_watch": 21, "action_save_cust_info": 22, "utter_purchase_process": 23, "utter_return_policy": 24, "utter_submit": 25, "action_track_order": 26, "action_show_watch_brands": 27, "utter_ask_order_id": 28, "order_form": 29}, "entities": {"brand": 0, "cust_name": 1, "cust_sex": 2, "gender": 3}, "slots": {"order_id_0": 0, "cust_sex_0": 1, "cust_name_0": 2, "brand_0": 3, "gender_0": 4}, "active_loop": {"order_form": 0}}, "action_texts": [], "entity_tag_specs": []}, "max_history": 5, "remove_duplicates": true}